xleapp_ios/__init__.py
xleapp_ios/helpers/parsers/__init__.py
xleapp_ios/helpers/parsers/ccl/ccl_bplist.py
xleapp_ios/helpers/parsers/ktx/ios_ktx2png.py
xleapp_ios/helpers/utils.py
xleapp_ios/plugins/__init__.py
xleapp_ios/plugins/accountConfiguration.py
xleapp_ios/plugins/accounts.py
xleapp_ios/plugins/addressBook.py
xleapp_ios/plugins/alarms.py
xleapp_ios/plugins/appConduit.py
xleapp_ios/plugins/appGrouplisting.py
xleapp_ios/plugins/appItunesMeta.py
xleapp_ios/plugins/appleMapsApplication.py
xleapp_ios/plugins/appleMapsGroup.py
xleapp_ios/plugins/appleMapsSearchHistory.py
xleapp_ios/plugins/applePodcastsEpisodes.py
xleapp_ios/plugins/applePodcastsShows.py
xleapp_ios/plugins/appleWalletCards.py
xleapp_ios/plugins/appleWalletPasses.py
xleapp_ios/plugins/appleWalletTransactions.py
xleapp_ios/plugins/appleWifiKnownNetworks.py
xleapp_ios/plugins/appleWifiScannedPrivateNetworks.py
xleapp_ios/plugins/applicationSnapshots.py
xleapp_ios/plugins/applicationState.py
xleapp_ios/plugins/bluetoothOtherLe.py
xleapp_ios/plugins/bluetoothPaired.py
xleapp_ios/plugins/bluetoothPairedLe.py
xleapp_ios/plugins/calendarIdentity.py
xleapp_ios/plugins/calendarItems.py
xleapp_ios/plugins/calendarList.py
xleapp_ios/plugins/callHistory.py
xleapp_ios/plugins/cashApp.py
xleapp_ios/plugins/cellularWireless.py
xleapp_ios/plugins/cloudkitNoteSharing.py
xleapp_ios/plugins/cloudkitParticipants.py
xleapp_ios/plugins/connectedDevices.py
xleapp_ios/plugins/deviceActivator.py
xleapp_ios/plugins/dhcpHotspotClients.py
xleapp_ios/plugins/dhcpReceivedList.py
xleapp_ios/plugins/discordAccounts.py
xleapp_ios/plugins/discordManifest.py
xleapp_ios/plugins/discordMessages.py
xleapp_ios/plugins/facebookMessengerCalls.py
xleapp_ios/plugins/facebookMessengerChats.py
xleapp_ios/plugins/facebookMessengerContacts.py
xleapp_ios/plugins/facebookMessengerConversationGroups.py
xleapp_ios/plugins/facebookMessengerSecretConversations.py
xleapp_ios/plugins/filesAppIcloudClientItems.py
xleapp_ios-0.1.3.dist-info/entry_points.txt
xleapp_ios-0.1.3.dist-info/WHEEL
xleapp_ios-0.1.3.dist-info/METADATA
xleapp_ios-0.1.3.dist-info/RECORD
